.gitattributes
.gitignore
LICENSE.txt
MANIFEST.in
README.md
_config.yml
caloriestracker.desktop
caloriestracker.pro
caloriestracker_autotest.py
setup.py
caloriestracker/__init__.py
caloriestracker/admin_pg.py
caloriestracker/call_by_name.py
caloriestracker/caloriestracker.py
caloriestracker/caloriestracker_console.py
caloriestracker/caloriestracker_maintenance.py
caloriestracker/casts.py
caloriestracker/connection_pg.py
caloriestracker/connection_pg_qt.py
caloriestracker/contribution.py
caloriestracker/database_update.py
caloriestracker/datetime_functions.py
caloriestracker/decorators.py
caloriestracker/github.py
caloriestracker/hardcoded_strings.py
caloriestracker/libcaloriestrackerfunctions.py
caloriestracker/libcaloriestrackertypes.py
caloriestracker/libmanagers.py
caloriestracker/mem.py
caloriestracker/npyscreen.py
caloriestracker/package_resources.py
caloriestracker/shortcuts.py
caloriestracker/sqlparser.py
caloriestracker/text_inputs.py
caloriestracker/translationlanguages.py
caloriestracker/version.py
caloriestracker.egg-info/PKG-INFO
caloriestracker.egg-info/SOURCES.txt
caloriestracker.egg-info/dependency_links.txt
caloriestracker.egg-info/entry_points.txt
caloriestracker.egg-info/not-zip-safe
caloriestracker.egg-info/requires.txt
caloriestracker.egg-info/top_level.txt
caloriestracker/i18n/caloriestracker_en.qm
caloriestracker/i18n/caloriestracker_en.ts
caloriestracker/i18n/caloriestracker_es.qm
caloriestracker/i18n/caloriestracker_es.ts
caloriestracker/i18n/caloriestracker_fr.qm
caloriestracker/i18n/caloriestracker_fr.ts
caloriestracker/i18n/caloriestracker_ro.qm
caloriestracker/i18n/caloriestracker_ro.ts
caloriestracker/i18n/caloriestracker_ru.qm
caloriestracker/i18n/caloriestracker_ru.ts
caloriestracker/images/14_layer_visible.png
caloriestracker/images/Money.png
caloriestracker/images/__init__.py
caloriestracker/images/add.png
caloriestracker/images/admin.png
caloriestracker/images/alarm_clock.png
caloriestracker/images/bank.png
caloriestracker/images/belgium.gif
caloriestracker/images/benchmark.png
caloriestracker/images/biometrics.png
caloriestracker/images/books.png
caloriestracker/images/bundle.png
caloriestracker/images/button_cancel.png
caloriestracker/images/button_ok.png
caloriestracker/images/cakes.png
