Metadata-Version: 2.1
Name: caloriestracker
Version: 0.8.0
Summary: Calories tracker system
Home-page: https://github.com/turulomio/caloriestracker
Author: Turulomio
Author-email: turulomio@yahoo.es
License: GPL-3
Keywords: calories tracker
Platform: UNKNOWN
Classifier: Development Status :: 4 - Beta
Classifier: Intended Audience :: End Users/Desktop
Classifier: License :: OSI Approved :: GNU General Public License v3 (GPLv3)
Classifier: Programming Language :: Python :: 3
